[
    {
        "id": "Action4/77927795",
        "value": 1147723700
    },
    {
        "id": "Action4/78035007",
        "value": 283162584
    },
    {
        "id": "Action4/78166929",
        "value": 255224855
    },
    {
        "id": "Action4/78213879",
        "value": 251315806
    },
    {
        "id": "Action4/78275441",
        "value": 206000000
    },
    {
        "id": "Action4/78303857",
        "value": 280375311
    },
    {
        "id": "Action4/78305228",
        "value": 109577732.379269
    },
    {
        "id": "Action4/78496698",
        "value": 260030345
    },
    {
        "id": "Action4/78573722",
        "value": 877832601
    },
    {
        "id": "Action4/78761292",
        "value": 110000000
    },
    {
        "id": "Action4/78926478",
        "value": 185000000
    },
    {
        "id": "Action4/78969175",
        "value": 102063017
    },
    {
        "id": "Action4/79021530",
        "value": 159519175.591617
    },
    {
        "id": "Action4/79024787",
        "value": 297283277
    },
    {
        "id": "Action4/79446270",
        "value": 130000000
    },
    {
        "id": "Action4/79452463",
        "value": 120818498.352958
    },
    {
        "id": "Action4/79452466",
        "value": 120806649.492299
    },
    {
        "id": "Action4/79466572",
        "value": 151655473
    },
    {
        "id": "Action4/79526453",
        "value": 267914175.73176
    },
    {
        "id": "Action4/79575545",
        "value": 129950847.177731
    },
    {
        "id": "Action4/79583313",
        "value": 148247096.664289
    },
    {
        "id": "Action4/79612261",
        "value": 149999970.163533
    },
    {
        "id": "Action4/79630007",
        "value": 897283277
    },
    {
        "id": "Action4/79631336",
        "value": 144998077.506711
    },
    {
        "id": "Action4/79631337",
        "value": 149605161.557671
    },
    {
        "id": "Action4/79631359",
        "value": 149999987.427672
    },
    {
        "id": "Action4/79634309",
        "value": 203000000
    },
    {
        "id": "Action4/79799686",
        "value": 136145159
    },
    {
        "id": "Action4/79810824",
        "value": 108171068.99602
    },
    {
        "id": "Action4/79849264",
        "value": 249832470.676308
    },
    {
        "id": "Action4/79849454",
        "value": 249832470.676308
    },
    {
        "id": "Action4/79849557",
        "value": 249832470.676308
    },
    {
        "id": "Action4/79849679",
        "value": 287724858.40347
    },
    {
        "id": "Action4/79930757",
        "value": 504132674
    },
    {
        "id": "Action4/79932456",
        "value": 400000000.0
    },
    {
        "id": "Action4/79995312",
        "value": 156701495.65322
    },
    {
        "id": "Action4/80200077",
        "value": 4500000000.0
    },
    {
        "id": "Action4/80326587",
        "value": 130000000
    },
    {
        "id": "Action4/80394933",
        "value": 249999940
    },
    {
        "id": "Action4/80682942",
        "value": 437902078
    },
    {
        "id": "Action4/81344004",
        "value": 330115558
    },
    {
        "id": "Action4/81429915",
        "value": 158867214
    },
    {
        "id": "Action4/81541374",
        "value": 156342897
    },
    {
        "id": "Action4/81577489",
        "value": 125172679.630661
    },
    {
        "id": "Action4/81848705",
        "value": 157684187
    },
    {
        "id": "Action4/82055332",
        "value": 250000000
    },
    {
        "id": "Action4/82672819",
        "value": 202937223
    },
    {
        "id": "Action4/82789340",
        "value": 274168332.871813
    },
    {
        "id": "Action4/83182398",
        "value": 102000000
    },
    {
        "id": "Action4/88108806",
        "value": 300044608
    },
    {
        "id": "Action4/88110593",
        "value": 627832641
    },
    {
        "id": "Action4/88163247",
        "value": 150000000
    },
    {
        "id": "Action4/88409411",
        "value": 845000000
    },
    {
        "id": "Action4/89147977",
        "value": 157826259.619169
    },
    {
        "id": "Action4/89281554",
        "value": 117459829.699117
    },
    {
        "id": "Action4/92187706",
        "value": 549999989
    },
    {
        "id": "Action4/75301227",
        "value": 126000000
    },
    {
        "id": "Action4/75361814",
        "value": 126000000
    },
    {
        "id": "Action4/75362223",
        "value": 144816996.964688
    },
    {
        "id": "Action4/75778831",
        "value": 300000000.0
    },
    {
        "id": "Action4/75907851",
        "value": 216000000
    },
    {
        "id": "Action4/75918417",
        "value": 315000000
    },
    {
        "id": "Action4/76125145",
        "value": 300000000.0
    },
    {
        "id": "Action4/76146559",
        "value": 125651380
    },
    {
        "id": "Action4/76172689",
        "value": 300000000.0
    },
    {
        "id": "Action4/76310515",
        "value": 136381359.132008
    },
    {
        "id": "Action4/76310804",
        "value": 153110415.849137
    },
    {
        "id": "Action4/76341538",
        "value": 319110415.849137
    },
    {
        "id": "Action4/76349772",
        "value": 118016778
    },
    {
        "id": "Action4/76350824",
        "value": 135832872
    },
    {
        "id": "Action4/76351893",
        "value": 300000000.0
    },
    {
        "id": "Action4/76389693",
        "value": 158000000
    },
    {
        "id": "Action4/76391958",
        "value": 158000000
    },
    {
        "id": "Action4/76392916",
        "value": 151922255.5149
    },
    {
        "id": "Action4/76428540",
        "value": 153075688.705017
    },
    {
        "id": "Action4/76494500",
        "value": 300000000.0
    },
    {
        "id": "Action4/76496033",
        "value": 700000001
    },
    {
        "id": "Action4/76517360",
        "value": 690000000
    },
    {
        "id": "Action4/76519385",
        "value": 113407243.98617
    },
    {
        "id": "Action4/76537423",
        "value": 107091917.634427
    },
    {
        "id": "Action4/76537960",
        "value": 160000000
    },
    {
        "id": "Action4/76538425",
        "value": 160000000
    },
    {
        "id": "Action4/76538573",
        "value": 191423015.43984
    },
    {
        "id": "Action4/76552968",
        "value": 1000000100
    },
    {
        "id": "Action4/76556771",
        "value": 399999994.467948
    },
    {
        "id": "Action4/76556772",
        "value": 399999993.42184
    },
    {
        "id": "Action4/76565238",
        "value": 399999988.247551
    },
    {
        "id": "Action4/76607248",
        "value": 399999997.400489
    },
    {
        "id": "Action4/76621919",
        "value": 500000000.0
    },
    {
        "id": "Action4/76622215",
        "value": 500000000.0
    },
    {
        "id": "Action4/76622947",
        "value": 487623697.41324
    },
    {
        "id": "Action4/76685582",
        "value": 1711672712.50067
    },
    {
        "id": "Action4/76724753",
        "value": 200856548.168802
    },
    {
        "id": "Action4/76746204",
        "value": 139321301.528444
    },
    {
        "id": "Action4/76746996",
        "value": 180195705.636551
    },
    {
        "id": "Action4/76762267",
        "value": 359000000
    },
    {
        "id": "Action4/76762287",
        "value": 359000000
    },
    {
        "id": "Action4/76762484",
        "value": 358787195.00283
    },
    {
        "id": "Action4/76778328",
        "value": 3000000000.0
    },
    {
        "id": "Action4/76883350",
        "value": 200012051.823723
    },
    {
        "id": "Action4/76976694",
        "value": 221451939.685411
    },
    {
        "id": "Action4/77472648",
        "value": 119458610.110026
    },
    {
        "id": "Action4/77474272",
        "value": 119458615.110026
    },
    {
        "id": "Action4/77474704",
        "value": 200155298.910894
    },
    {
        "id": "Action4/77489050",
        "value": 200696677.390122
    },
    {
        "id": "Action4/77503143",
        "value": 880271921.13115
    },
    {
        "id": "Action4/77621665",
        "value": 200211105.929609
    },
    {
        "id": "Action4/77687448",
        "value": 200690792.13211
    },
    {
        "id": "Action4/77691391",
        "value": 150000000
    },
    {
        "id": "Action4/77712703",
        "value": 143174576
    },
    {
        "id": "Action4/77774675",
        "value": 372514301.8621
    },
    {
        "id": "Action4/77781111",
        "value": 207303718.143912
    }
]